board.py
board-1.0.dist-info/METADATA
board-1.0.dist-info/WHEEL
board-1.0.dist-info/top_level.txt
board-1.0.dist-info/RECORD
