Metadata-Version: 1.2
Name: board
Version: 1.0
Summary: Standard Board mechanism for Dojo tasks
Home-page: https://github.com/tjguk/dojo-board
Author: Tim Golden
Author-email: mail@timgolden.me.uk
Maintainer: Tim Golden
Maintainer-email: mail@timgolden.me.uk
License: unlicensed
Platform: UNKNOWN
Classifier: Environment :: Console
Classifier: Intended Audience :: Developers
Classifier: Operating System :: OS Independent
Classifier: Programming Language :: Python
Classifier: Programming Language :: Python :: 2
Classifier: Programming Language :: Python :: 2.7
Classifier: Programming Language :: Python :: 3
